Workbook
Name Slicer_Charger_Type: #N/A
Name Slicer_City: #N/A
Name Slicer_Customer_Type: #N/A
Name Slicer_Region: #N/A
Name Slicer_Station_Type: #N/A

Sheet Raw_Data
A1: Session_ID | B1: Session_Date | C1: Station_ID | D1: Region | E1: City | F1: Station_Type | G1: Charger_Type | H1: Customer_Type | I1: Payment_Mode | J1: Energy_kWh | K1: Price_per_kWh | L1: Discount_% | M1: Discount_Amount | N1: Revenue | O1: Electricity_Cost | P1: Network_Cost | Q1: Payment_Fee | R1: Maintenance_Cost | S1: Refund_Amount | T1: SLA_Penalty | U1: Total_Cost | V1: Profit | W1: Profit_Flag | X1: Session_Status | Y1: Downtime_Min | Z1: Queue_Min | AA1: Downtime_Bucket | AB1: SLA_Breached | AC1: Support_Tickets | AD1: Risk_Flag | AE1: SLA_Breached_Flag
A2: 100001 | B2: 45954 | C2: 1073 | D2: North | E2: Noida | F2: Mall | G2: DC_120kW | H2: Retail | I2: UPI | J2: 26.73 | K2: 18.51 | L2: 15 | M2: 74.22 | N2: 420.55 | O2: 215.87 | P2: 8.25 | Q2: 3.46 | R2: 1.91 | S2: 0 | T2: 0 | U2: 229.49 | V2: 191.06 | W2: Profit | X2: Completed | Y2: 13 | Z2: 10 | AA2: 0-15 | AB2: No | AC2: 0 | AD2: Healthy | AE2: =IF(AB2="Yes",1,0) -> 0
A3: 100002 | B3: 45935 | C3: 1138 | D3: North | E3: Delhi | F3: Residential | G3: DC_120kW | H3: Retail | I3: Card | J3: 15.07 | K3: 18.07 | L3: 20 | M3: 54.46 | N3: 217.85 | O3: 93.31 | P3: 15.19 | Q3: 4.08 | R3: 4.54 | S3: 0 | T3: 0 | U3: 117.12 | V3: 100.73 | W3: Profit | X3: Completed | Y3: 36 | Z3: 3 | AA3: 30+ | AB3: Yes | AC3: 1 | AD3: At Risk | AE3: =IF(AB3="Yes",1,0) -> 1
A4: 100003 | B4: 45950 | C4: 1005 | D4: North | E4: Delhi | F4: Mall | G4: DC_30kW | H4: Retail | I4: Card | J4: 12.55 | K4: 16.55 | L4: 10 | M4: 20.77 | N4: 186.93 | O4: 84.33 | P4: 11.38 | Q4: 3.12 | R4: 6.15 | S4: 0 | T4: 0 | U4: 104.98 | V4: 81.95 | W4: Profit | X4: Completed | Y4: 11 | Z4: 9 | AA4: 0-15 | AB4: No | AC4: 0 | AD4: Healthy | AE4: =IF(AB4="Yes",1,0) -> 0
A5: 100004 | B5: 45946 | C5: 1060 | D5: South | E5: Hyderabad | F5: Office Park | G5: DC_60kW | H5: RideShare | I5: Card | J5: 12.67 | K5: 16.64 | L5: 10 | M5: 21.08 | N5: 189.75 | O5: 96.31 | P5: 7.72 | Q5: 3.16 | R5: 10.77 | S5: 0 | T5: 0 | U5: 117.96 | V5: 71.79 | W5: Profit | X5: Completed | Y5: 22 | Z5: 1 | AA5: 16-30 | AB5: Yes | AC5: 2 | AD5: At Risk | AE5: =IF(AB5="Yes",1,0) -> 1
A6: 100005 | B6: 45972 | C6: 1030 | D6: South | E6: Bengaluru | F6: Residential | G6: DC_30kW | H6: Retail | I6: Wallet | J6: 39.98 | K6: 15.33 | L6: 0 | M6: 0 | N6: 612.89 | O6: 201.69 | P6: 12.6 | Q6: 7.35 | R6: 7.41 | S6: 230.71 | T6: 0 | U6: 459.76 | V6: 153.13 | W6: Profit | X6: Failed | Y6: 13 | Z6: 14 | AA6: 0-15 | AB6: Yes | AC6: 3 | AD6: At Risk | AE6: =IF(AB6="Yes",1,0) -> 1
A7: 100006 | B7: 46006 | C7: 1007 | D7: South | E7: Kochi | F7: Mall | G7: DC_60kW | H7: Fleet | I7: Card | J7: 30.03 | K7: 17.91 | L7: 5 | M7: 26.89 | N7: 510.95 | O7: 215.26 | P7: 8.25 | Q7: 8.07 | R7: 12.5 | S7: 262.68 | T7: 20.33 | U7: 527.09 | V7: -16.14 | W7: Loss | X7: Failed | Y7: 2 | Z7: 4 | AA7: 0-15 | AB7: Yes | AC7: 1 | AD7: At Risk | AE7: =IF(AB7="Yes",1,0) -> 1
A8: 100007 | B8: 46022 | C8: 1143 | D8: North | E8: Noida | F8: Mall | G8: DC_30kW | H8: Retail | I8: UPI | J8: 31.89 | K8: 16.16 | L8: 10 | M8: 51.53 | N8: 463.81 | O8: 230.53 | P8: 6.45 | Q8: 3.61 | R8: 2.89 | S8: 0 | T8: 0 | U8: 243.48 | V8: 220.33 | W8: Profit | X8: Completed | Y8: 25 | Z8: 21 | AA8: 16-30 | AB8: Yes | AC8: 1 | AD8: At Risk | AE8: =IF(AB8="Yes",1,0) -> 1
A9: 100008 | B9: 46020 | C9: 1055 | D9: West | E9: Ahmedabad | F9: Highway Hub | G9: DC_30kW | H9: RideShare | I9: UPI | J9: 23.75 | K9: 15.51 | L9: 20 | M9: 73.67 | N9: 294.69 | O9: 162.85 | P9: 6.06 | Q9: 2.58 | R9: 12.99 | S9: 0 | T9: 0 | U9: 184.48 | V9: 110.21 | W9: Profit | X9: Completed | Y9: 1 | Z9: 3 | AA9: 0-15 | AB9: No | AC9: 1 | AD9: Healthy | AE9: =IF(AB9="Yes",1,0) -> 0
A10: 100009 | B10: 45938 | C10: 1093 | D10: North | E10: Chandigarh | F10: Highway Hub | G10: AC_7kW | H10: Retail | I10: UPI | J10: 9.25 | K10: 13.19 | L10: 0 | M10: 0 | N10: 122.01 | O10: 64.46 | P10: 11.1 | Q10: 0.85 | R10: 0 | S10: 0 | T10: 0 | U10: 76.41 | V10: 45.6 | W10: Profit | X10: Completed | Y10: 14 | Z10: 2 | AA10: 0-15 | AB10: No | AC10: 0 | AD10: Healthy | AE10: =IF(AB10="Yes",1,0) -> 0
A11: 100010 | B11: 45957 | C11: 1125 | D11: East | E11: Bhubaneswar | F11: Office Park | G11: DC_30kW | H11: Retail | I11: Wallet | J11: 43.43 | K11: 14.75 | L11: 15 | M11: 96.09 | N11: 544.5 | O11: 294.81 | P11: 7.18 | Q11: 7.69 | R11: 2.71 | S11: 0 | T11: 0 | U11: 312.39 | V11: 232.11 | W11: Profit | X11: Completed | Y11: 3 | Z11: 5 | AA11: 0-15 | AB11: No | AC11: 0 | AD11: Healthy | AE11: =IF(AB11="Yes",1,0) -> 0
A12: 100011 | B12: 45977 | C12: 1069 | D12: South | E12: Kochi | F12: Highway Hub | G12: DC_30kW | H12: Retail | I12: UPI | J12: 15.55 | K12: 15.96 | L12: 10 | M12: 24.82 | N12: 223.36 | O12: 123.78 | P12: 11.86 | Q12: 1.74 | R12: 5.63 | S12: 218.94 | T12: 0 | U12: 361.95 | V12: -138.59 | W12: Loss | X12: Cancelled | Y12: 10 | Z12: 0 | AA12: 0-15 | AB12: No | AC12: 2 | AD12: At Risk | AE12: =IF(AB12="Yes",1,0) -> 0
A13: 100012 | B13: 45952 | C13: 1067 | D13: North | E13: Delhi | F13: Highway Hub | G13: AC_7kW | H13: Fleet | I13: UPI | J13: 22.46 | K13: 12.49 | L13: 5 | M13: 14.03 | N13: 266.5 | O13: 198.46 | P13: 9.04 | Q13: 1.96 | R13: 11.88 | S13: 0 | T13: 0 | U13: 221.34 | V13: 45.16 | W13: Profit | X13: Completed | Y13: 4 | Z13: 5 | AA13: 0-15 | AB13: No | AC13: 0 | AD13: Healthy | AE13: =IF(AB13="Yes",1,0) -> 0
... A3001: 103000 | B3001: 45960 | C3001: 1082 | D3001: East | E3001: Kolkata | F3001: Highway Hub | G3001: DC_120kW | H3001: Fleet | I3001: UPI | J3001: 26.4 | K3001: 18.67 | L3001: 0 | M3001: 0 | N3001: 492.89 | O3001: 210.95 | P3001: 4.93 | Q3001: 3.45 | R3001: 7.1 | S3001: 0 | T3001: 0 | U3001: 226.43 | V3001: 266.46 | W3001: Profit | X3001: Completed | Y3001: 1 | Z3001: 1 | AA3001: 0-15 | AB3001: No | AC3001: 0 | AD3001: Healthy | AE3001: =IF(AB3001="Yes",1,0) -> 0

Sheet Project_Blueprint
A1: Section | B1: Item | C1: Notes
A2: Context | B2: Business | C2: EV charging network operations analytics
A3: Context | B3: Time period | C3: Oct-Dec 2025 (92 days)
A4: Context | B4: Granularity | C4: Each row = charging session
A5: KPIs | B5: Total Revenue | C5: Sum Revenue
A6: KPIs | B6: Total Profit | C6: Sum Profit
A7: KPIs | B7: Profit Margin % | C7: Profit/Revenue
A8: KPIs | B8: Sessions | C8: Count of Session_ID
A9: KPIs | B9: % SLA Breached | C9: % Yes in SLA_Breached
A10: KPIs | B10: Revenue at Risk (Refunds+Failed) | C10: Revenue linked to Failed/Cancelled + Refunds
A11: Segments | B11: Region | C11: Use slicers
A12: Segments | B12: City | C12: Use slicers
... A20: Core Questions | B20: What should Ops Head fix in 7 days? | C20: Top 3 actions + owners

Sheet Pivot_Calculations
B2: Count of Session_ID | C2: Sum of Revenue | D2: Sum of Total_Cost | E2: Sum of Profit | F2: Sum of Profit_Margin % | G2: Sum of % SLA_Breached
B3: 3000 | C3: 1089159.3 | D3: 688035.33 | E3: 401123.97 | F3: 0.3682877 | G3: 0.36166667
B5: Region | F5: Station | I5: Charger | L5: Discount and Customer | P5: City
B7: Region | C7: Sum of Profit | F7: Station_type | G7: Sum of Profit | I7: Charger_type | J7: Sum of Profit | L7: Discount % | M7: Count of Session_ID | P7: City | Q7: Sum of Revenue | R7: Sum of Profit | T7: Session_status | U7: Sum of Revenue
B8: East | C8: 77356.24 | F8: Fuel Station | G8: 78680.48 | I8: AC_7kW | J8: 57301.06 | L8: 0 | M8: 1257 | P8: Ahmedabad | Q8: 76959.96 | R8: 29562.97 | T8: Cancelled | U8: 67580.07
B9: North | C9: 109143.9 | F9: Highway Hub | G9: 94189.17 | I9: DC_120kW | J9: 112145.85 | L9: 5 | M9: 629 | P9: Bengaluru | Q9: 71920.51 | R9: 24686.75 | T9: Completed | U9: 934264.04
B10: South | C10: 104354.1 | F10: Mall | G10: 64530.02 | I10: DC_30kW | J10: 122058.2 | L10: 10 | M10: 566 | P10: Bhubaneswar | Q10: 51538.58 | R10: 19902.5 | T10: Failed | U10: 87315.19
B11: West | C11: 110269.73 | F11: Office Park | G11: 69516.09 | I11: DC_60kW | J11: 109618.86 | L11: 15 | M11: 373 | P11: Chandigarh | Q11: 70909.54 | R11: 25514.96 | T11: Grand Total | U11: 1089159.3
B12: Grand Total | C12: 401123.97 | F12: Residential | G12: 94208.21 | I12: Grand Total | J12: 401123.97 | L12: 20 | M12: 175 | P12: Chennai | Q12: 74661.07 | R12: 27109.85
F13: Grand Total | G13: 401123.97 | L13: Grand Total | M13: 3000 | P13: Delhi | Q13: 72204.83 | R13: 26066.52 | T13: =GETPIVOTDATA("Sum of Revenue",$T$7,"Session_status",$T$8) -> 67580.07 | U13: =GETPIVOTDATA("Sum of Revenue",$T$7,"Session_status",$T$10) -> 87315.19
B14: Region | C14: Sum of % SLA_Breached | I14: charger_type | J14: Sum of % SLA_Breached | P14: Gurugram | Q14: 78917.75 | R14: 29531.35
B15: East | C15: 0.070666667 | F15: Station_type | G15: Sum of % SLA_Breached | I15: AC_7kW | J15: 0.137 | L15: Customer_type | M15: Sum of Revenue | N15: Sum of Profit | P15: Guwahati | Q15: 48297.72 | R15: 17787.37 | T15: =GETPIVOTDATA("Sum of Revenue",T7,"Session_status",T8)+GETPIVOTDATA("Sum of Revenue",T7,"Session_status",T10) -> 154895.26
B16: North | C16: 0.101 | F16: Fuel Station | G16: 0.073666667 | I16: DC_120kW | J16: 0.052 | L16: Fleet | M16: 273925.63 | N16: 100130.23 | P16: Hyderabad | Q16: 70566.82 | R16: 24261.22
B17: South | C17: 0.095333333 | F17: Highway Hub | G17: 0.079 | I17: DC_30kW | J17: 0.103 | L17: Retail | M17: 675040.21 | N17: 250931.82 | P17: Jaipur | Q17: 65557.76 | R17: 26053.79
B18: West | C18: 0.094666667 | F18: Mall | G18: 0.064666667 | I18: DC_60kW | J18: 0.069666667 | L18: RideShare | M18: 140193.46 | N18: 50061.92 | P18: Kochi | Q18: 78931.28 | R18: 28296.28
B19: Grand Total | C19: 0.36166667 | F19: Office Park | G19: 0.062 | I19: Grand Total | J19: 0.36166667 | L19: Grand Total | M19: 1089159.3 | N19: 401123.97 | P19: Kolkata | Q19: 49538.38 | R19: 18463.15
F20: Residential | G20: 0.082333333 | P20: Mumbai | Q20: 77575.29 | R20: 28432.71
F21: Grand Total | G21: 0.36166667 | I21: charger_type | J21: Sum of Downtime_Min | L21: Discount % | M21: Sum of Profit | P21: Noida | Q21: 71991.45 | R21: 28031.07
I22: AC_7kW | J22: 12819 | L22: 0 | M22: 196091.43 | P22: Patna | Q22: 55746.79 | R22: 21203.22
F23: Station_type | G23: Sum of Downtime_Min | I23: DC_120kW | J23: 5163 | L23: 5 | M23: 83359.1 | P23: Pune | Q23: 73841.57 | R23: 26220.26
F24: Fuel Station | G24: 6842 | I24: DC_30kW | J24: 9670 | L24: 10 | M24: 68047.72 | P24: Grand Total | Q24: 1089159.3 | R24: 401123.97
F25: Highway Hub | G25: 7593 | I25: DC_60kW | J25: 6296 | L25: 15 | M25: 37879.23
F26: Mall | G26: 5879 | I26: Grand Total | J26: 33948 | L26: 20 | M26: 15746.49 | P26: City | Q26: Sum of % SLA_Breached
F27: Office Park | G27: 5731 | L27: Grand Total | M27: 401123.97 | P27: Ahmedabad | Q27: 0.022333333
F28: Residential | G28: 7903 | P28: Bengaluru | Q28: 0.025
F29: Grand Total | G29: 33948 | P29: Bhubaneswar | Q29: 0.018333333
P30: Chandigarh | Q30: 0.020333333
P31: Chennai | Q31: 0.022666667
P32: Delhi | Q32: 0.028666667
P33: Gurugram | Q33: 0.029
P34: Guwahati | Q34: 0.016
P35: Hyderabad | Q35: 0.022333333
P36: Jaipur | Q36: 0.019666667
P37: Kochi | Q37: 0.025333333
P38: Kolkata | Q38: 0.014333333
P39: Mumbai | Q39: 0.029
P40: Noida | Q40: 0.023
P41: Patna | Q41: 0.022
... P43: Grand Total | Q43: 0.36166667

Sheet Dashboard
A1: Profit and Ops Performance Dashboard- EV Charging Network and Operations
A4: Total Revenue | E4: Total Cost | I4: Total Profit | M4: Profit Margin % | Q4: % SLA Breached | U4: Revenue at Risk
A5: =Pivot_Calculations!C3 -> 1089159.3 | E5: =Pivot_Calculations!D3 -> 688035.33 | I5: =Pivot_Calculations!E3 -> 401123.97 | M5: =I5/A5 -> 0.3682877 | Q5: =Pivot_Calculations!G3 -> 0.36166667 | U5: =GETPIVOTDATA("Sum of Revenue",Pivot_Calculations!T7,"Session_status",Pivot_Calculations!T8)+GETPIVOTDATA("Sum of Revenue",Pivot_Calculations!T7,"Session_status",Pivot_Calculations!T10) -> 154895.26

Sheet Insights_Notes
A2: Insights
A3: 14.22 % Revenue is at risk due to Failed and Cancelled sessions.
A4: Discount rise from 10 to 20, erased profit from 68,000 to 15,000
A5: Charger AC_7kW at Residental and Fuel Station has highest Downtime.
A6: Delhi and Mumbai have Highest SLA Breachesat 2.87 and 2.90 %.
A8: Root Cause Hypotheses
A9: Charging Stations may lack maintainance and purchase system may have error leading to failure/cancellations.
A10: Customers,after a certain point, don’t focus on discounts.
A11: System or maintainance issue leads to charger being unavailable
A12: High vehicle density leads to poor availibilty and failed/cancellations.
A15: CEO Recommendations
A16: Recommendation | KPI Impact | Priority | Owner
... A20: Expand charging stations and manage sessions | Reduce Risk Revenue and SLA Breaches | High | Ops Head
